<APPLANG>
  <CAM>
    <DESCRIPTION>Visningsnavn / Video Enhet</DESCRIPTION>
    <HEADER>CAM</HEADER>
    <DISPLAYNAME>CAM</DISPLAYNAME>
    <FULLSCREEN>FULLSKJERM</FULLSCREEN>
    <SAVESNAPSHOT>LAGRE FOTO</SAVESNAPSHOT>
    <CLOSE>LUKK</CLOSE>
    <RECORD>SPILL INN</RECORD>
    <FULLRESTORE>GJENOPPRETT</FULLRESTORE>
  </CAM>
  <SETUP>
    <HEADER>CAM</HEADER>
    <ON>P&#197;</ON>
    <OFF>AV</OFF>
    <SAVE>LAGRE</SAVE>
    <CLOSE>LUKK</CLOSE>
    <NONE>Ingen</NONE>
    <RECORDING>SPILLER INN...</RECORDING>
    <DISPLAYNAME>SKJERM NAVN</DISPLAYNAME>
    <ANTENNA>ANTENNE</ANTENNA>
    <CABLE>KABEL</CABLE>
    <VIDEODEVICE>VIDEO ENHET</VIDEODEVICE>
    <VIDEODEVICES>VIDEO ENHETER</VIDEODEVICES>
    <AUDIODEVICE>AUDIO ENHET</AUDIODEVICE>
    <AUDIODEVICES>AUDIO ENHETER</AUDIODEVICES>
    <VIDEOSOURCE>VIDEO KILDE</VIDEOSOURCE>
    <VIDEOSOURCES>VIDEO KILDER</VIDEOSOURCES>
    <AUDIOSOURCE>AUDIO KILDE</AUDIOSOURCE>
    <AUDIOSOURCES>AUDIO KILDER</AUDIOSOURCES>
    <TUNESOURCES>JUSTERINGSKILDER</TUNESOURCES>
    <TUNESOURCE>JUSTERINGSKILDE</TUNESOURCE>
    <FRAMERATE>OPPDATERINGS HASTIGHET</FRAMERATE>
    <FRAMERATES>OPPDATERINGS HASTIGHETER</FRAMERATES>
    <SAVEPATH>LAGRINGSSTI FOR FOTO</SAVEPATH>
    <FULLSCREEN>START FULLSKJERM</FULLSCREEN>
    <BUTTON1TEXT>ANGI VISNINGSNAVN</BUTTON1TEXT>
    <BUTTON2TEXT>ANGI VIDEO ENHET</BUTTON2TEXT>
    <BUTTON3TEXT>VELG AUDIO ENHET</BUTTON3TEXT>
    <BUTTON4TEXT>VELG TV KILDE</BUTTON4TEXT>
    <BUTTON5TEXT>VELG AUDIO KILDE</BUTTON5TEXT>
    <BUTTON6TEXT>VELG OPPDATERINGSHASTIGHET</BUTTON6TEXT>
    <BUTTON7TEXT>VELG JUSTERINGSKILDE</BUTTON7TEXT>
    <OVERWRITETEXT>OVERSKRIV GJELDENDE INNSTILLINGER?</OVERWRITETEXT>
    <LOCATIONSTEXT>VELG PLASSERING</LOCATIONSTEXT>
    <LOCATIONS>PLASSERINGER</LOCATIONS>
    <CAMDISPLAY>CAM SKJERM</CAMDISPLAY>
    <WIDESCREEN>WIDESCREEN</WIDESCREEN>
    <FLIPSCREEN>FLIPSCREEN</FLIPSCREEN>
  </SETUP>
</APPLANG>
